mockdata/__init__.py
mockdata/setup.py
radarpipeline/__init__.py
radarpipeline/radarpipeline.py
radarpipeline/common/__init__.py
radarpipeline/common/constants.py
radarpipeline/common/logger.py
radarpipeline/common/utils.py
radarpipeline/datalib/__init__.py
radarpipeline/datalib/abc.py
radarpipeline/datalib/radar_data.py
radarpipeline/datalib/radar_user_data.py
radarpipeline/datalib/radar_variable_data.py
radarpipeline/datatypes/__init__.py
radarpipeline/datatypes/data_types.py
radarpipeline/features/__init__.py
radarpipeline/features/feature.py
radarpipeline/features/feature_group.py
radarpipeline/features/feature_loader.py
radarpipeline/features/custom/__init__.py
radarpipeline/features/custom/tabularize.py
radarpipeline/io/__init__.py
radarpipeline/io/abc.py
radarpipeline/io/connection.py
radarpipeline/io/downloader.py
radarpipeline/io/ingestion.py
radarpipeline/io/reader.py
radarpipeline/io/sampler.py
radarpipeline/io/writer.py
radarpipeline/project/__init__.py
radarpipeline/project/project.py
radarpipeline/project/sparkengine.py
radarpipeline/project/validations.py
radarpipeline/visualization/__init__.py
temp/__init__.py
temp/__main__.py
tests/__init__.py
tmp/__init__.py
tmp/__main__.py
radarpipeline-2.1.0.dist-info/LICENSE
radarpipeline-2.1.0.dist-info/METADATA
radarpipeline-2.1.0.dist-info/WHEEL
radarpipeline-2.1.0.dist-info/top_level.txt
radarpipeline-2.1.0.dist-info/RECORD
