Metadata-Version: 2.1
Name: radarpipeline
Version: 2.1.0
Summary: A python feature generation and visualization package use with RADAR-base project data.
Home-page: https://github.com/RADAR-base/radarpipeline
Download-URL: https://github.com/RADAR-base/radarpipeline/archive/refs/tags/v2.1.0.tar.gz
Author: Heet Sankesara, Amos Folarin
Author-email: heet.sankesara@kcl.ac.uk, amos.folarin@kcl.ac.uk
License: Apache
Keywords: mhealth,pipeline,big-data
Classifier: Programming Language :: Python :: 3
Classifier: License :: OSI Approved :: Apache Software License
Classifier: Intended Audience :: Science/Research
Classifier: Programming Language :: Python :: 3.10
Classifier: Programming Language :: Python :: 3.11
Classifier: Programming Language :: Python :: 3.12
License-File: LICENSE
Requires-Dist: twine ==5.1.0
Requires-Dist: pyYaml ==6.0.1
Requires-Dist: pandas ==2.2.2
Requires-Dist: numpy ==1.26.4
Requires-Dist: scipy ==1.14.0
Requires-Dist: pyspark[sql] ==3.5.1
Requires-Dist: GitPython >=3.1.41
Requires-Dist: strictyaml ==1.7.3
Requires-Dist: paramiko ==3.4.0
Requires-Dist: avro ==1.11.3
Requires-Dist: pyarrow ==16.1.0
